dutch_flag/__init__.py
dutch_flag-0.1.2.dist-info/LICENSE
dutch_flag-0.1.2.dist-info/METADATA
dutch_flag-0.1.2.dist-info/WHEEL
dutch_flag-0.1.2.dist-info/top_level.txt
dutch_flag-0.1.2.dist-info/RECORD
