Metadata-Version: 2.1
Name: dutch_flag
Version: 0.1.2
Summary: A minimalistic python library solving the Dutch national flag problem.
Home-page: https://github.com/sergei-shteiner/dutch_flag
Author: Sergei Shteiner
Author-email: sergei.shteiner@gmail.com
Classifier: Programming Language :: Python :: 3
Classifier: License :: OSI Approved :: MIT License
Classifier: Operating System :: OS Independent
License-File: LICENSE
